engramdb_py-0.1.1.dist-info/METADATA
engramdb_py-0.1.1.dist-info/WHEEL
_engramdb/_engramdb.cpython-313-darwin.so
engramdb_py-0.1.1.dist-info/RECORD
