Metadata-Version: 2.4
Name: engramdb-py
Version: 0.1.1
Classifier: Programming Language :: Python :: 3.8
Classifier: Programming Language :: Python :: 3.9
Classifier: Programming Language :: Python :: 3.10
Classifier: Programming Language :: Python :: 3.11
Classifier: Programming Language :: Rust
Classifier: License :: OSI Approved :: MIT License
Classifier: Development Status :: 3 - Alpha
Classifier: Intended Audience :: Developers
Classifier: Intended Audience :: Science/Research
Classifier: Topic :: Database
Classifier: Topic :: Scientific/Engineering :: Artificial Intelligence
Requires-Dist: numpy>=1.20.0
Summary: Python bindings for the EngramDB database
Author: Niko <engramdb@disequi.com>
Author-email: Niko <engramdb@disequi.com>
License: MIT
Requires-Python: >=3.8
Project-URL: Repository, https://github.com/nkkko/engramdb
Project-URL: Documentation, https://github.com/nkkko/engramdb/python/README.md
